LICENSE.txt
MANIFEST.in
README.rst
setup.py
jojo_office.egg-info/PKG-INFO
jojo_office.egg-info/SOURCES.txt
jojo_office.egg-info/dependency_links.txt
jojo_office.egg-info/requires.txt
jojo_office.egg-info/top_level.txt
office/__init__.py
office/base.py
office/devtools.py
office/excel.py
office/http.py
office/pdf.py
office/photo.py
office/ppt.py
office/requirements.txt
office/util.py
office/variable.py
office/video.py
office/win32.py
office/word.py
office/doc/__init__.py
office/examples/__init__.py
office/examples/excel/__init__.py
office/examples/excel/datafile.py
office/examples/excel/datafile.xlsx
office/examples/excel/excel_examples_en.py
office/examples/excel/newfile.xlsx
office/examples/excel/~$datafile.xlsx
office/examples/excel/chinese/__init__.py
office/examples/excel/chinese/datafile.xlsx
office/examples/excel/chinese/excel_examples_cn.py
office/examples/pptx/__init__.py
office/examples/pptx/ppt_automation_en.md
office/examples/pptx/ppt_examples_en.py
office/test/test_xls.py
office/test/test_xls.xlsx